[
  {
    "id": 19,
    "attribute_id": 224,
    "store_id": 1,
    "tooltip": ""
  },
  {
    "id": 20,
    "attribute_id": 224,
    "store_id": 0,
    "tooltip": ""
  },
  {
    "id": 21,
    "attribute_id": 228,
    "store_id": 1,
    "tooltip": ""
  },
  {
    "id": 22,
    "attribute_id": 228,
    "store_id": 0,
    "tooltip": ""
  },
  {
    "id": 25,
    "attribute_id": 225,
    "store_id": 1,
    "tooltip": ""
  },
  {
    "id": 26,
    "attribute_id": 225,
    "store_id": 0,
    "tooltip": ""
  },
  {
    "id": 29,
    "attribute_id": 232,
    "store_id": 1,
    "tooltip": ""
  },
  {
    "id": 30,
    "attribute_id": 232,
    "store_id": 0,
    "tooltip": ""
  },
  {
    "id": 31,
    "attribute_id": 233,
    "store_id": 1,
    "tooltip": ""
  },
  {
    "id": 32,
    "attribute_id": 233,
    "store_id": 0,
    "tooltip": ""
  }
]
