[{"entity_id":1,"increment_id":"000000001","state":2,"store_id":1,"store_name":"Main Website\nKlondike\nDefault St","order_id":31,"order_increment_id":"000000031","order_created_at":"2019-03-24 18:44:31","customer_name":"Yurii Malikov","customer_email":"malikov.yurii.a@gmail.com","customer_group_id":1,"payment_method":"cashondelivery","store_currency_code":"UAH","order_currency_code":"UAH","base_currency_code":"UAH","global_currency_code":"UAH","billing_name":"Юрий Маликов","billing_address":"№200,Киев,Киевская,-","shipping_address":"№200,Киев,Киевская,-","shipping_information":"Адресная доставка - Новая почта","subtotal":540,"shipping_and_handling":0,"grand_total":540,"created_at":"2019-03-24 20:42:26","updated_at":"2019-03-24 20:42:26","base_grand_total":540},{"entity_id":2,"increment_id":"000000002","state":2,"store_id":1,"store_name":"Main Website\nKlondike\nDefault St","order_id":34,"order_increment_id":"000000034","order_created_at":"2019-04-02 21:32:20","customer_name":"Иван Иванов","customer_email":"ivanov@k.com","customer_group_id":1,"payment_method":"checkmo","store_currency_code":"UAH","order_currency_code":"UAH","base_currency_code":"UAH","global_currency_code":"UAH","billing_name":"Иван Иванов","billing_address":"отделение неизвестно,Киев,Киевская,11111","shipping_address":"НП №3,Киев,Киевская","shipping_information":"Доставка на отделения - Новая почта","subtotal":600,"shipping_and_handling":0,"grand_total":600,"created_at":"2019-04-02 21:44:39","updated_at":"2019-04-02 21:44:39","base_grand_total":600},{"entity_id":3,"increment_id":"000000003","state":2,"store_id":1,"store_name":"Main Website\nKlondike\nDefault St","order_id":68,"order_increment_id":"000000068","order_created_at":"2019-06-10 18:35:26","customer_name":"Test Test","customer_email":"vokilam.d@gmail.com","customer_group_id":1,"payment_method":"checkmo","store_currency_code":"UAH","order_currency_code":"UAH","base_currency_code":"UAH","global_currency_code":"UAH","billing_name":"Test Test","billing_address":"test,test,test,-","shipping_address":"test,test,test,-","shipping_information":"Адресная доставка Новой Почтой - Новая почта","subtotal":485,"shipping_and_handling":0,"grand_total":485,"created_at":"2019-06-10 18:44:12","updated_at":"2019-06-10 18:44:12","base_grand_total":485},{"entity_id":4,"increment_id":"000000004","state":2,"store_id":1,"store_name":"Main Website\nKlondike\nDefault St","order_id":69,"order_increment_id":"000000069","order_created_at":"2019-06-10 19:20:01","customer_name":"Yurii Malikov","customer_email":"malikov.yurii.a@gmail.com","customer_group_id":1,"payment_method":"checkmo","store_currency_code":"UAH","order_currency_code":"UAH","base_currency_code":"UAH","global_currency_code":"UAH","billing_name":"Yurii Malikov","billing_address":"123,Kyiv,Kyiv City,-","shipping_address":"123,Kyiv,Kyiv City,-","shipping_information":"Адресная доставка Новой Почтой - Новая почта","subtotal":1853,"shipping_and_handling":0,"grand_total":1853,"created_at":"2019-06-11 14:28:57","updated_at":"2019-06-11 14:28:57","base_grand_total":1853},{"entity_id":5,"increment_id":"000000005","state":2,"store_id":1,"store_name":"Main Website\nKlondike\nDefault St","order_id":39,"order_increment_id":"000000039","order_created_at":"2019-05-20 23:43:32","customer_name":"Yurii Malikov","customer_email":"malikov.yurii.a@gmail.com","customer_group_id":1,"payment_method":"checkmo","store_currency_code":"UAH","order_currency_code":"UAH","base_currency_code":"UAH","global_currency_code":"UAH","billing_name":"Юрий Маликов","billing_address":"№200,Киев,Киевская,-","shipping_address":"№200,Киев,Киевская,-","shipping_information":"Адресная доставка - Новая почта","subtotal":610,"shipping_and_handling":0,"grand_total":610,"created_at":"2019-06-11 14:33:36","updated_at":"2019-06-11 14:33:36","base_grand_total":610},{"entity_id":6,"increment_id":"000000006","state":2,"store_id":1,"store_name":"Main Website\nKlondike\nDefault St","order_id":40,"order_increment_id":"000000040","order_created_at":"2019-05-25 22:52:34","customer_name":"Test Test","customer_email":"vokilam.d@gmail.com","customer_group_id":1,"payment_method":"cashondelivery","store_currency_code":"UAH","order_currency_code":"UAH","base_currency_code":"UAH","global_currency_code":"UAH","billing_name":"Test Test","billing_address":"test,test,test,-","shipping_address":"test,test,test,-","shipping_information":"Доставка на отделения - Новая почта","subtotal":760,"shipping_and_handling":0,"grand_total":760,"created_at":"2019-06-11 17:30:10","updated_at":"2019-06-11 17:30:10","base_grand_total":760},{"entity_id":7,"increment_id":"000000007","state":2,"store_id":1,"store_name":"Main Website\nKlondike\nDefault St","order_id":76,"order_increment_id":"000000076","order_created_at":"2019-06-11 21:12:24","customer_name":"","customer_email":"sadsa@dfd.com","customer_group_id":0,"payment_method":"cashondelivery","store_currency_code":"UAH","order_currency_code":"UAH","base_currency_code":"UAH","global_currency_code":"UAH","billing_name":"qwe qwe","billing_address":"asdas,Kiev,Kiev,-","shipping_address":"asdas,Kiev,Kiev,-","shipping_information":"Доставка на отделение Новой Почты - Новая почта","subtotal":245,"shipping_and_handling":0,"grand_total":245,"created_at":"2019-06-11 21:50:35","updated_at":"2019-06-11 21:50:35","base_grand_total":245},{"entity_id":8,"increment_id":"000000008","state":2,"store_id":1,"store_name":"Main Website\nKlondike\nDefault St","order_id":77,"order_increment_id":"000000077","order_created_at":"2019-06-15 07:44:48","customer_name":"","customer_email":"malikov.yurii.a@gmail.com","customer_group_id":0,"payment_method":"checkmo","store_currency_code":"UAH","order_currency_code":"UAH","base_currency_code":"UAH","global_currency_code":"UAH","billing_name":"Юрий Маликов","billing_address":"245,Киев,Киевская,-","shipping_address":"245,Киев,Киевская,-","shipping_information":"Доставка на отделение Новой Почты - Новая почта","subtotal":62,"shipping_and_handling":0,"grand_total":62,"created_at":"2019-06-15 08:33:05","updated_at":"2019-06-15 08:36:33","base_grand_total":62},{"entity_id":9,"increment_id":"000000009","state":2,"store_id":1,"store_name":"Main Website\nKlondike\nDefault St","order_id":83,"order_increment_id":"000000083","order_created_at":"2019-06-17 10:58:13","customer_name":"Yurii Malikov","customer_email":"malikov.yurii.a@gmail.com","customer_group_id":1,"payment_method":"cashondelivery","store_currency_code":"UAH","order_currency_code":"UAH","base_currency_code":"UAH","global_currency_code":"UAH","billing_name":"Юрий Маликов","billing_address":"245,Киев,Киевская,-","shipping_address":"245,Киев,Киевская,-","shipping_information":"Доставка на отделение Новой Почты - Новая почта","subtotal":135,"shipping_and_handling":0,"grand_total":135,"created_at":"2019-06-17 10:58:38","updated_at":"2019-06-17 10:58:38","base_grand_total":135},{"entity_id":10,"increment_id":"000000010","state":2,"store_id":1,"store_name":"Main Website\nKlondike\nDefault St","order_id":84,"order_increment_id":"000000084","order_created_at":"2019-06-17 11:50:29","customer_name":"Yurii Malikov","customer_email":"malikov.yurii.a@gmail.com","customer_group_id":1,"payment_method":"cashondelivery","store_currency_code":"UAH","order_currency_code":"UAH","base_currency_code":"UAH","global_currency_code":"UAH","billing_name":"Юрий Маликов","billing_address":"245,Киев,Киевская,-","shipping_address":"245,Киев,Киевская,-","shipping_information":"Адресная доставка Новой Почтой - Новая почта","subtotal":79,"shipping_and_handling":0,"grand_total":79,"created_at":"2019-06-17 11:52:58","updated_at":"2019-06-17 11:52:58","base_grand_total":79},{"entity_id":11,"increment_id":"000000011","state":2,"store_id":1,"store_name":"Main Website\nKlondike\nDefault St","order_id":97,"order_increment_id":"000000097","order_created_at":"2019-07-08 17:41:43","customer_name":"Yurii Malikov","customer_email":"malikov.yurii.a@gmail.com","customer_group_id":1,"payment_method":"wayforpay","store_currency_code":"UAH","order_currency_code":"UAH","base_currency_code":"UAH","global_currency_code":"UAH","billing_name":"Юрий Маликов","billing_address":"245,Киев,Киевская,-","shipping_address":"245,Киев,Киевская,-","shipping_information":"Доставка на отделение Новой Почты - Новая почта","subtotal":29,"shipping_and_handling":0,"grand_total":29,"created_at":"2019-07-08 19:25:13","updated_at":"2019-07-08 19:25:13","base_grand_total":29},{"entity_id":12,"increment_id":"000000012","state":2,"store_id":1,"store_name":"Main Website\nKlondike\nDefault St","order_id":180,"order_increment_id":"000000180","order_created_at":"2019-07-29 19:06:42","customer_name":"Александр Гальченко","customer_email":"sa.galchenko@gmail.com","customer_group_id":1,"payment_method":"cashondelivery","store_currency_code":"UAH","order_currency_code":"UAH","base_currency_code":"UAH","global_currency_code":"UAH","billing_name":"Sys Admin","billing_address":"31231,sgd,Kiev,36000","shipping_address":"31231,sgd,Kiev,36000","shipping_information":"Доставка на отделение Новой Почты - Новая почта","subtotal":399,"shipping_and_handling":0,"grand_total":399,"created_at":"2019-07-29 19:08:36","updated_at":"2019-07-29 19:08:36","base_grand_total":399},{"entity_id":13,"increment_id":"000000013","state":2,"store_id":1,"store_name":"Main Website\nKlondike\nDefault St","order_id":181,"order_increment_id":"000000181","order_created_at":"2019-07-29 21:47:34","customer_name":"Yurii Malikov","customer_email":"malikov.yurii.a@gmail.com","customer_group_id":1,"payment_method":"checkmo","store_currency_code":"UAH","order_currency_code":"UAH","base_currency_code":"UAH","global_currency_code":"UAH","billing_name":"Юрий Маликов","billing_address":"245,Киев,Киевская,-","shipping_address":"245,Киев,Киевская,-","shipping_information":"Доставка на отделение Новой Почты - Новая почта","subtotal":645,"shipping_and_handling":0,"grand_total":645,"created_at":"2019-07-29 21:54:43","updated_at":"2019-07-29 21:54:43","base_grand_total":645},{"entity_id":14,"increment_id":"000000014","state":2,"store_id":1,"store_name":"Main Website\nKlondike\nDefault St","order_id":182,"order_increment_id":"000000182","order_created_at":"2019-07-29 21:56:41","customer_name":"Yurii Malikov","customer_email":"malikov.yurii.a@gmail.com","customer_group_id":1,"payment_method":"cashondelivery","store_currency_code":"UAH","order_currency_code":"UAH","base_currency_code":"UAH","global_currency_code":"UAH","billing_name":"Юрий Маликов","billing_address":"245,Киев,Киевская,-","shipping_address":"245,Киев,Киевская,-","shipping_information":"Доставка на отделение Новой Почты - Новая почта","subtotal":99,"shipping_and_handling":0,"grand_total":96,"created_at":"2019-07-29 22:04:14","updated_at":"2019-07-29 22:04:14","base_grand_total":96},{"entity_id":15,"increment_id":"000000015","state":2,"store_id":1,"store_name":"Main Website\nKlondike\nDefault St","order_id":183,"order_increment_id":"000000183","order_created_at":"2019-07-29 22:05:42","customer_name":"Yurii Malikov","customer_email":"malikov.yurii.a@gmail.com","customer_group_id":1,"payment_method":"cashondelivery","store_currency_code":"UAH","order_currency_code":"UAH","base_currency_code":"UAH","global_currency_code":"UAH","billing_name":"Юрий Маликов","billing_address":"245,Киев,Киевская,-","shipping_address":"245,Киев,Киевская,-","shipping_information":"Доставка на отделение Новой Почты - Новая почта","subtotal":771,"shipping_and_handling":0,"grand_total":771,"created_at":"2019-07-29 22:06:47","updated_at":"2019-07-29 22:06:47","base_grand_total":771},{"entity_id":16,"increment_id":"000000016","state":2,"store_id":1,"store_name":"Main Website\nKlondike\nDefault St","order_id":186,"order_increment_id":"000000186","order_created_at":"2019-07-29 23:21:10","customer_name":"Yurii Malikov","customer_email":"malikov.yurii.a@gmail.com","customer_group_id":1,"payment_method":"cashondelivery","store_currency_code":"UAH","order_currency_code":"UAH","base_currency_code":"UAH","global_currency_code":"UAH","billing_name":"Юрий Маликов","billing_address":"245,Киев,Киевская,-","shipping_address":"245,Киев,Киевская,-","shipping_information":"Доставка на отделение Новой Почты - Новая почта","subtotal":55,"shipping_and_handling":0,"grand_total":52,"created_at":"2019-07-29 23:22:32","updated_at":"2019-07-29 23:22:32","base_grand_total":52},{"entity_id":17,"increment_id":"000000017","state":2,"store_id":1,"store_name":"Main Website\nKlondike\nDefault St","order_id":201,"order_increment_id":"000000201","order_created_at":"2019-07-31 21:03:27","customer_name":"Yurii Malikov","customer_email":"malikov.yurii.a@gmail.com","customer_group_id":1,"payment_method":"cashondelivery","store_currency_code":"UAH","order_currency_code":"UAH","base_currency_code":"UAH","global_currency_code":"UAH","billing_name":"Юрий Маликов","billing_address":"245,Киев,Киевская,-","shipping_address":"245,Киев,Киевская,-","shipping_information":"Доставка на отделение Новой Почты - Новая почта","subtotal":435,"shipping_and_handling":0,"grand_total":435,"created_at":"2019-07-31 21:05:14","updated_at":"2019-07-31 21:05:14","base_grand_total":435},{"entity_id":18,"increment_id":"000000018","state":2,"store_id":1,"store_name":"Main Website\nKlondike\nDefault St","order_id":224,"order_increment_id":"000000224","order_created_at":"2019-08-01 20:53:05","customer_name":"donis makaronis","customer_email":"vokilam.d@gmail.com","customer_group_id":1,"payment_method":"wayforpay","store_currency_code":"UAH","order_currency_code":"UAH","base_currency_code":"UAH","global_currency_code":"UAH","billing_name":"donis makaronis","billing_address":"ylittsa,gorod,obl,index","shipping_address":"ylittsa,gorod,obl,index","shipping_information":"Адресная доставка Новой Почтой - Новая почта","subtotal":440,"shipping_and_handling":0,"grand_total":440,"created_at":"2019-08-01 20:56:47","updated_at":"2019-08-01 20:56:47","base_grand_total":440},{"entity_id":19,"increment_id":"000000019","state":2,"store_id":1,"store_name":"Main Website\nKlondike\nDefault St","order_id":219,"order_increment_id":"000000219","order_created_at":"2019-08-01 19:49:22","customer_name":"Yurii Malikov","customer_email":"malikov.yurii.a@gmail.com","customer_group_id":1,"payment_method":"cashondelivery","store_currency_code":"UAH","order_currency_code":"UAH","base_currency_code":"UAH","global_currency_code":"UAH","billing_name":"Юрий Маликов","billing_address":"245,Киев,Киевская,-","shipping_address":"245,Киев,Киевская,-","shipping_information":"Доставка на отделение Новой Почты - Новая почта","subtotal":1025,"shipping_and_handling":0,"grand_total":1022,"created_at":"2019-08-01 22:12:28","updated_at":"2019-08-01 22:12:28","base_grand_total":1022},{"entity_id":20,"increment_id":"000000020","state":2,"store_id":1,"store_name":"Main Website\nKlondike\nDefault St","order_id":228,"order_increment_id":"000000228","order_created_at":"2019-08-01 22:14:29","customer_name":"Yurii Malikov","customer_email":"malikov.yurii.a@gmail.com","customer_group_id":1,"payment_method":"cashondelivery","store_currency_code":"UAH","order_currency_code":"UAH","base_currency_code":"UAH","global_currency_code":"UAH","billing_name":"Юрий Маликов","billing_address":"245,Киев,Киевская,-","shipping_address":"245,Киев,Киевская,-","shipping_information":"Доставка на отделение Новой Почты - Новая почта","subtotal":1427,"shipping_and_handling":0,"grand_total":1356,"created_at":"2019-08-01 22:16:16","updated_at":"2019-08-01 22:16:16","base_grand_total":1356},{"entity_id":21,"increment_id":"000000021","state":2,"store_id":1,"store_name":"Main Website\nKlondike\nDefault St","order_id":229,"order_increment_id":"000000229","order_created_at":"2019-08-01 22:18:06","customer_name":"Yurii Malikov","customer_email":"malikov.yurii.a@gmail.com","customer_group_id":1,"payment_method":"cashondelivery","store_currency_code":"UAH","order_currency_code":"UAH","base_currency_code":"UAH","global_currency_code":"UAH","billing_name":"Юрий Маликов","billing_address":"245,Киев,Киевская,-","shipping_address":"245,Киев,Киевская,-","shipping_information":"Доставка на отделение Новой Почты - Новая почта","subtotal":1329,"shipping_and_handling":0,"grand_total":1315,"created_at":"2019-08-01 22:18:41","updated_at":"2019-08-01 22:18:41","base_grand_total":1315},{"entity_id":22,"increment_id":"000000022","state":2,"store_id":1,"store_name":"Main Website\nKlondike\nDefault St","order_id":230,"order_increment_id":"000000230","order_created_at":"2019-08-01 22:21:17","customer_name":"Yurii Malikov","customer_email":"malikov.yurii.a@gmail.com","customer_group_id":1,"payment_method":"cashondelivery","store_currency_code":"UAH","order_currency_code":"UAH","base_currency_code":"UAH","global_currency_code":"UAH","billing_name":"Юрий Маликов","billing_address":"245,Киев,Киевская,-","shipping_address":"245,Киев,Киевская,-","shipping_information":"Доставка на отделение Новой Почты - Новая почта","subtotal":7148,"shipping_and_handling":0,"grand_total":7129,"created_at":"2019-08-01 22:21:54","updated_at":"2019-08-01 22:21:54","base_grand_total":7129},{"entity_id":23,"increment_id":"000000023","state":2,"store_id":1,"store_name":"Main Website\nKlondike\nDefault St","order_id":262,"order_increment_id":"000000262","order_created_at":"2019-08-03 00:14:44","customer_name":"a fn a ln","customer_email":"a@gmail.com","customer_group_id":1,"payment_method":"checkmo","store_currency_code":"UAH","order_currency_code":"UAH","base_currency_code":"UAH","global_currency_code":"UAH","billing_name":"a fn a ln","billing_address":"a str,a c i,acsp,1","shipping_address":"a str,a c i,acsp,1","shipping_information":"Доставка на отделение Новой Почты - Новая почта","subtotal":645,"shipping_and_handling":0,"grand_total":645,"created_at":"2019-08-03 00:15:09","updated_at":"2019-08-03 00:15:09","base_grand_total":645},{"entity_id":24,"increment_id":"000000024","state":2,"store_id":1,"store_name":"Main Website\nKlondike\nDefault St","order_id":263,"order_increment_id":"000000263","order_created_at":"2019-08-03 16:44:23","customer_name":"donis makaronis","customer_email":"vokilam.d@gmail.com","customer_group_id":1,"payment_method":"cashondelivery","store_currency_code":"UAH","order_currency_code":"UAH","base_currency_code":"UAH","global_currency_code":"UAH","billing_name":"donis makaronis","billing_address":"ylittsa,gorod,obl,index","shipping_address":"ylittsa,gorod,obl,index","shipping_information":"Доставка на отделение Новой Почты - Новая почта","subtotal":1083,"shipping_and_handling":0,"grand_total":1083,"created_at":"2019-08-03 16:45:32","updated_at":"2019-08-03 16:45:32","base_grand_total":1083},{"entity_id":25,"increment_id":"000000025","state":2,"store_id":1,"store_name":"Main Website\nKlondike\nDefault St","order_id":266,"order_increment_id":"000000266","order_created_at":"2019-08-03 22:53:26","customer_name":"Yurii Malikov","customer_email":"malikov.yurii.a@gmail.com","customer_group_id":1,"payment_method":"checkmo","store_currency_code":"UAH","order_currency_code":"UAH","base_currency_code":"UAH","global_currency_code":"UAH","billing_name":"Юрий Маликов","billing_address":"245,Киев,Киевская,-","shipping_address":"245,Киев,Киевская,-","shipping_information":"Адресная доставка Новой Почтой - Новая почта","subtotal":58,"shipping_and_handling":0,"grand_total":52,"created_at":"2019-08-03 22:54:47","updated_at":"2019-08-03 22:54:47","base_grand_total":52},{"entity_id":26,"increment_id":"000000026","state":2,"store_id":1,"store_name":"Main Website\nKlondike\nDefault St","order_id":285,"order_increment_id":"000000285","order_created_at":"2019-08-04 21:16:33","customer_name":"Yurii Malikov","customer_email":"malikov.yurii.a@gmail.com","customer_group_id":1,"payment_method":"cashondelivery","store_currency_code":"UAH","order_currency_code":"UAH","base_currency_code":"UAH","global_currency_code":"UAH","billing_name":"Юрий Маликов","billing_address":"245,Киев,Киевская,-","shipping_address":"245,Киев,Киевская,-","shipping_information":"Доставка на отделение Новой Почты - Новая почта","subtotal":771,"shipping_and_handling":0,"grand_total":771,"created_at":"2019-08-04 21:22:21","updated_at":"2019-08-04 21:22:21","base_grand_total":771},{"entity_id":27,"increment_id":"000000027","state":2,"store_id":1,"store_name":"Main Website\nKlondike\nDefault St","order_id":286,"order_increment_id":"000000286","order_created_at":"2019-08-04 21:38:16","customer_name":"Yurii Malikov","customer_email":"malikov.yurii.a@gmail.com","customer_group_id":1,"payment_method":"checkmo","store_currency_code":"UAH","order_currency_code":"UAH","base_currency_code":"UAH","global_currency_code":"UAH","billing_name":"Юрий Маликов","billing_address":"245,Киев,Киевская,-","shipping_address":"245,Киев,Киевская,-","shipping_information":"Доставка на отделение Новой Почты - Новая почта","subtotal":2550,"shipping_and_handling":0,"grand_total":2473,"created_at":"2019-08-04 21:41:26","updated_at":"2019-08-04 21:41:26","base_grand_total":2473},{"entity_id":28,"increment_id":"000000028","state":2,"store_id":1,"store_name":"Main Website\nKlondike\nDefault St","order_id":289,"order_increment_id":"000000288-1","order_created_at":"2019-08-04 21:59:48","customer_name":"Yurii Malikov","customer_email":"malikov.yurii.a@gmail.com","customer_group_id":1,"payment_method":"checkmo","store_currency_code":"UAH","order_currency_code":"UAH","base_currency_code":"UAH","global_currency_code":"UAH","billing_name":"Юрий Маликов","billing_address":"Вацлава Гавела 6в, кв 62,Киев,Киевская,-","shipping_address":"Вацлава Гавела 6в, кв 623,Киев,Киевская,-","shipping_information":"Адресная доставка Новой Почтой - Новая почта","subtotal":11166,"shipping_and_handling":0,"grand_total":11096,"created_at":"2019-08-04 22:01:19","updated_at":"2019-08-04 22:01:19","base_grand_total":11096},{"entity_id":29,"increment_id":"000000029","state":2,"store_id":1,"store_name":"Main Website\nKlondike\nDefault St","order_id":292,"order_increment_id":"000000291","order_created_at":"2019-08-04 22:22:22","customer_name":"Yurii Malikov","customer_email":"malikov.yurii.a@gmail.com","customer_group_id":1,"payment_method":"wayforpay","store_currency_code":"UAH","order_currency_code":"UAH","base_currency_code":"UAH","global_currency_code":"UAH","billing_name":"Юрий Маликов","billing_address":"Вацлава Гавела 6в, кв 65,Киев,Киевская,-","shipping_address":"Вацлава Гавела 6в, кв 65,Киев,Киевская,-","shipping_information":"Адресная доставка Новой Почтой - Новая почта","subtotal":10,"shipping_and_handling":0,"grand_total":9,"created_at":"2019-08-04 22:28:25","updated_at":"2019-08-04 22:28:25","base_grand_total":9},{"entity_id":30,"increment_id":"000000030","state":2,"store_id":1,"store_name":"Main Website\nKlondike\nDefault St","order_id":315,"order_increment_id":"000000314","order_created_at":"2019-08-07 14:11:06","customer_name":"","customer_email":"elenapozolotchik@gmail.com","customer_group_id":0,"payment_method":"cashondelivery","store_currency_code":"UAH","order_currency_code":"UAH","base_currency_code":"UAH","global_currency_code":"UAH","billing_name":"Елена Светличная","billing_address":"999,Харьков,Донецкая,-","shipping_address":"999,Харьков,Донецкая,-","shipping_information":"Доставка на отделение Новой Почты - Новая почта","subtotal":10,"shipping_and_handling":0,"grand_total":10,"created_at":"2019-08-07 16:13:21","updated_at":"2019-08-07 16:13:21","base_grand_total":10},{"entity_id":31,"increment_id":"000000031","state":2,"store_id":1,"store_name":"Main Website\nKlondike\nDefault St","order_id":316,"order_increment_id":"000000315","order_created_at":"2019-08-07 15:29:37","customer_name":"","customer_email":"elenapozolotchik@gmail.com","customer_group_id":0,"payment_method":"cashondelivery","store_currency_code":"UAH","order_currency_code":"UAH","base_currency_code":"UAH","global_currency_code":"UAH","billing_name":"Елена Огонькова","billing_address":"1,наш,наша,-","shipping_address":"000,наш,наша,-","shipping_information":"Доставка на отделение Новой Почты - Новая почта","subtotal":985,"shipping_and_handling":0,"grand_total":985,"created_at":"2019-08-07 16:55:03","updated_at":"2019-08-07 16:55:03","base_grand_total":985},{"entity_id":32,"increment_id":"000000032","state":2,"store_id":1,"store_name":"Main Website\nKlondike\nDefault St","order_id":336,"order_increment_id":"000000335","order_created_at":"2019-08-08 14:27:50","customer_name":"","customer_email":"elenapozolotchik@gmail.com","customer_group_id":0,"payment_method":"cashondelivery","store_currency_code":"UAH","order_currency_code":"UAH","base_currency_code":"UAH","global_currency_code":"UAH","billing_name":"Елена Огонькова","billing_address":"1,наш,наша,-","shipping_address":"000,наш,наша,-","shipping_information":"Доставка на отделение Новой Почты - Новая почта","subtotal":2955,"shipping_and_handling":0,"grand_total":2955,"created_at":"2019-08-08 14:33:39","updated_at":"2019-08-08 14:33:39","base_grand_total":2955},{"entity_id":33,"increment_id":"000000033","state":2,"store_id":1,"store_name":"Main Website\nKlondike\nDefault St","order_id":338,"order_increment_id":"000000337","order_created_at":"2019-08-08 14:44:24","customer_name":"","customer_email":"malikovaoi@ukr.net","customer_group_id":0,"payment_method":"checkmo","store_currency_code":"UAH","order_currency_code":"UAH","base_currency_code":"UAH","global_currency_code":"UAH","billing_name":"Елена Прекрасная","billing_address":"1,Хороший,наша,-","shipping_address":"1,Хороший,наша,-","shipping_information":"Доставка на отделение Новой Почты - Новая почта","subtotal":10,"shipping_and_handling":0,"grand_total":10,"created_at":"2019-08-08 14:45:44","updated_at":"2019-08-08 14:45:44","base_grand_total":10},{"entity_id":34,"increment_id":"000000034","state":2,"store_id":1,"store_name":"Main Website\nKlondike\nDefault St","order_id":344,"order_increment_id":"000000343","order_created_at":"2019-08-14 17:43:18","customer_name":"","customer_email":"sa@root.ua","customer_group_id":0,"payment_method":"cashondelivery","store_currency_code":"UAH","order_currency_code":"UAH","base_currency_code":"UAH","global_currency_code":"UAH","billing_name":"Sys Admin","billing_address":"31231,sgd,Kiev,-","shipping_address":"31231,sgd,Kiev,-","shipping_information":"Доставка на отделение Новой Почты - Новая почта","subtotal":210,"shipping_and_handling":0,"grand_total":210,"created_at":"2019-08-14 17:44:16","updated_at":"2019-08-14 17:44:16","base_grand_total":210},{"entity_id":35,"increment_id":"000000035","state":2,"store_id":1,"store_name":"Main Website\nKlondike\nDefault St","order_id":356,"order_increment_id":"000000355","order_created_at":"2019-08-16 10:05:30","customer_name":"","customer_email":"oksanabatyuk@gmail.com","customer_group_id":0,"payment_method":"wayforpay","store_currency_code":"UAH","order_currency_code":"UAH","base_currency_code":"UAH","global_currency_code":"UAH","billing_name":"Оксана Жуковская","billing_address":"Днепр, 181 отд.,0995017177,Днепровская,-","shipping_address":"Днепр, 181 отд.,0995017177,Днепровская,-","shipping_information":"Доставка на отделение Новой Почты - Новая почта","subtotal":298,"shipping_and_handling":0,"grand_total":298,"created_at":"2019-08-16 10:42:46","updated_at":"2019-08-16 10:42:46","base_grand_total":298},{"entity_id":36,"increment_id":"000000036","state":2,"store_id":1,"store_name":"Main Website\nKlondike\nDefault St","order_id":357,"order_increment_id":"000000356","order_created_at":"2019-08-16 13:32:12","customer_name":"Юрий Юрьевич Сапонов","customer_email":"zzzzsaponov@gmail.com","customer_group_id":1,"payment_method":"cashondelivery","store_currency_code":"UAH","order_currency_code":"UAH","base_currency_code":"UAH","global_currency_code":"UAH","billing_name":"Юрий Юрьевич Сапонов","billing_address":"1,Славянск,Донецкая,1","shipping_address":"1,Славянск,Донецкая,1","shipping_information":"Доставка на отделение Новой Почты - Новая почта","subtotal":149,"shipping_and_handling":0,"grand_total":149,"created_at":"2019-08-16 13:33:22","updated_at":"2019-08-16 13:33:22","base_grand_total":149},{"entity_id":37,"increment_id":"000000037","state":2,"store_id":1,"store_name":"Main Website\nKlondike\nDefault St","order_id":358,"order_increment_id":"000000357","order_created_at":"2019-08-16 13:39:01","customer_name":"Ефросиния Игоревна Смих","customer_email":"zzzzsmih@gmail.com","customer_group_id":1,"payment_method":"checkmo","store_currency_code":"UAH","order_currency_code":"UAH","base_currency_code":"UAH","global_currency_code":"UAH","billing_name":"Ефросиния Игоревна Смих","billing_address":"30,Одесса,Одесская,30","shipping_address":"30,Одесса,Одесская,30","shipping_information":"Доставка на отделение Новой Почты - Новая почта","subtotal":1062,"shipping_and_handling":0,"grand_total":1062,"created_at":"2019-08-16 13:39:41","updated_at":"2019-08-16 13:39:41","base_grand_total":1062},{"entity_id":38,"increment_id":"000000038","state":2,"store_id":1,"store_name":"Main Website\nKlondike\nDefault St","order_id":359,"order_increment_id":"000000358","order_created_at":"2019-08-16 13:44:23","customer_name":"Александр Брык","customer_email":"zzzzbrik@gmail.com","customer_group_id":1,"payment_method":"checkmo","store_currency_code":"UAH","order_currency_code":"UAH","base_currency_code":"UAH","global_currency_code":"UAH","billing_name":"Александр Брык","billing_address":"2,Бахмут,Донецкая,2","shipping_address":"2,Бахмут,Донецкая,2","shipping_information":"Доставка на отделение Новой Почты - Новая почта","subtotal":137,"shipping_and_handling":0,"grand_total":137,"created_at":"2019-08-16 13:46:02","updated_at":"2019-08-16 13:46:02","base_grand_total":137},{"entity_id":39,"increment_id":"000000039","state":2,"store_id":1,"store_name":"Main Website\nKlondike\nDefault St","order_id":360,"order_increment_id":"000000359","order_created_at":"2019-08-16 13:49:03","customer_name":"Михаил Рыбак","customer_email":"zzzzribak@gmail.com","customer_group_id":1,"payment_method":"checkmo","store_currency_code":"UAH","order_currency_code":"UAH","base_currency_code":"UAH","global_currency_code":"UAH","billing_name":"Михаил Рыбак","billing_address":"31,Одесса,Одесская,31","shipping_address":"31,Одесса,Одесская,31","shipping_information":"Доставка на отделение Новой Почты - Новая почта","subtotal":324,"shipping_and_handling":0,"grand_total":324,"created_at":"2019-08-16 13:49:54","updated_at":"2019-08-16 13:49:54","base_grand_total":324},{"entity_id":40,"increment_id":"000000040","state":2,"store_id":1,"store_name":"Main Website\nKlondike\nDefault St","order_id":361,"order_increment_id":"000000360","order_created_at":"2019-08-16 13:57:16","customer_name":"Дмитрий Романив","customer_email":"zzzzromaniv@gmail.com","customer_group_id":1,"payment_method":"cashondelivery","store_currency_code":"UAH","order_currency_code":"UAH","base_currency_code":"UAH","global_currency_code":"UAH","billing_name":"Дмитрий Романив","billing_address":"273,Киев,Киевская,273","shipping_address":"273,Киев,Киевская,273","shipping_information":"Доставка на отделение Новой Почты - Новая почта","subtotal":265,"shipping_and_handling":0,"grand_total":265,"created_at":"2019-08-16 13:59:45","updated_at":"2019-08-16 13:59:45","base_grand_total":265},{"entity_id":41,"increment_id":"000000041","state":2,"store_id":1,"store_name":"Main Website\nKlondike\nDefault St","order_id":362,"order_increment_id":"000000361","order_created_at":"2019-08-16 14:03:58","customer_name":"Светлана Ивановна Загоранская","customer_email":"zzzzzagoranskaya@gmail.com","customer_group_id":1,"payment_method":"cashondelivery","store_currency_code":"UAH","order_currency_code":"UAH","base_currency_code":"UAH","global_currency_code":"UAH","billing_name":"Светлана Ивановна Загоранская","billing_address":"1,Раздельная,Одесская,1","shipping_address":"1,Раздельная,Одесская,1","shipping_information":"Доставка на отделение Новой Почты - Новая почта","subtotal":348,"shipping_and_handling":0,"grand_total":348,"created_at":"2019-08-16 14:04:45","updated_at":"2019-08-16 14:04:45","base_grand_total":348},{"entity_id":42,"increment_id":"000000042","state":2,"store_id":1,"store_name":"Main Website\nKlondike\nDefault St","order_id":363,"order_increment_id":"000000362","order_created_at":"2019-08-16 14:21:39","customer_name":"Роман Илюшик","customer_email":"zzzzilyushik@gmail.com","customer_group_id":1,"payment_method":"checkmo","store_currency_code":"UAH","order_currency_code":"UAH","base_currency_code":"UAH","global_currency_code":"UAH","billing_name":"Роман Илюшик","billing_address":"2,Ковель,Волынская,2","shipping_address":"2,Ковель,Волынская,2","shipping_information":"Доставка на отделение Новой Почты - Новая почта","subtotal":1275,"shipping_and_handling":0,"grand_total":1275,"created_at":"2019-08-16 14:22:16","updated_at":"2019-08-16 14:22:16","base_grand_total":1275},{"entity_id":43,"increment_id":"000000043","state":2,"store_id":1,"store_name":"Main Website\nKlondike\nDefault St","order_id":366,"order_increment_id":"000000366","order_created_at":"2019-08-16 15:05:59","customer_name":"Сергей Хащенко","customer_email":"xachenko@yahoo.com","customer_group_id":1,"payment_method":"checkmo","store_currency_code":"UAH","order_currency_code":"UAH","base_currency_code":"UAH","global_currency_code":"UAH","billing_name":"Сергей Хащенко","billing_address":"Отделение №1,Лисичанск,Луганская область,1","shipping_address":"Отделение №1,Лисичанск,Луганская область,-","shipping_information":"Доставка на отделение Новой Почты - Новая почта","subtotal":665,"shipping_and_handling":0,"grand_total":665,"created_at":"2019-08-16 15:07:04","updated_at":"2019-08-16 15:07:04","base_grand_total":665},{"entity_id":44,"increment_id":"000000044","state":2,"store_id":1,"store_name":"Main Website\nKlondike\nDefault St","order_id":367,"order_increment_id":"000000367","order_created_at":"2019-08-16 15:17:01","customer_name":"Наталья Калениковна Сацик","customer_email":"zzzzsazik@gmail.com","customer_group_id":1,"payment_method":"checkmo","store_currency_code":"UAH","order_currency_code":"UAH","base_currency_code":"UAH","global_currency_code":"UAH","billing_name":"Наталья Калениковна Сацик","billing_address":"10,Львов,Львовская,10","shipping_address":"10,Львов,Львовская,10","shipping_information":"Доставка на отделение Новой Почты - Новая почта","subtotal":2660,"shipping_and_handling":0,"grand_total":2660,"created_at":"2019-08-16 17:26:00","updated_at":"2019-08-16 17:26:00","base_grand_total":2660},{"entity_id":45,"increment_id":"000000045","state":2,"store_id":1,"store_name":"Main Website\nKlondike\nDefault St","order_id":369,"order_increment_id":"000000369","order_created_at":"2019-08-16 17:48:22","customer_name":"Александр Йосипенко","customer_email":"zzzzyosipenko@gmail.com","customer_group_id":1,"payment_method":"checkmo","store_currency_code":"UAH","order_currency_code":"UAH","base_currency_code":"UAH","global_currency_code":"UAH","billing_name":"Александр Йосипенко","billing_address":"13,Чернигов,Черниговская,13","shipping_address":"13,Чернигов,Черниговская,13","shipping_information":"Доставка на отделение Новой Почты - Новая почта","subtotal":618,"shipping_and_handling":0,"grand_total":618,"created_at":"2019-08-16 17:50:59","updated_at":"2019-08-16 17:50:59","base_grand_total":618},{"entity_id":46,"increment_id":"000000046","state":2,"store_id":1,"store_name":"Main Website\nKlondike\nDefault St","order_id":374,"order_increment_id":"000000374","order_created_at":"2019-08-17 16:13:42","customer_name":"Александр Полищук","customer_email":"zzzzpolishyk@gmail.com","customer_group_id":1,"payment_method":"cashondelivery","store_currency_code":"UAH","order_currency_code":"UAH","base_currency_code":"UAH","global_currency_code":"UAH","billing_name":"Александр Полищук","billing_address":"204,Киев,Киевская,204","shipping_address":"204,Киев,Киевская,204","shipping_information":"Доставка на отделение Новой Почты - Новая почта","subtotal":2519,"shipping_and_handling":0,"grand_total":2519,"created_at":"2019-08-17 16:14:17","updated_at":"2019-08-17 16:14:17","base_grand_total":2519},{"entity_id":47,"increment_id":"000000047","state":2,"store_id":1,"store_name":"Main Website\nKlondike\nDefault St","order_id":375,"order_increment_id":"000000375","order_created_at":"2019-08-17 16:19:39","customer_name":"Сергей Александрович Бусыгин","customer_email":"zzzzbusigin@gmail.com","customer_group_id":1,"payment_method":"cashondelivery","store_currency_code":"UAH","order_currency_code":"UAH","base_currency_code":"UAH","global_currency_code":"UAH","billing_name":"Сергей Александрович Бусыгин","billing_address":"26,Днепр,Денпровская,26","shipping_address":"26,Днепр,Денпровская,26","shipping_information":"Доставка на отделение Новой Почты - Новая почта","subtotal":430,"shipping_and_handling":0,"grand_total":430,"created_at":"2019-08-17 16:20:43","updated_at":"2019-08-17 16:20:43","base_grand_total":430},{"entity_id":48,"increment_id":"000000048","state":2,"store_id":1,"store_name":"Main Website\nKlondike\nDefault St","order_id":376,"order_increment_id":"000000376","order_created_at":"2019-08-17 16:27:57","customer_name":"Александр Сергеевич Гаврилин","customer_email":"zzzzgavrilin@gmail.com","customer_group_id":1,"payment_method":"cashondelivery","store_currency_code":"UAH","order_currency_code":"UAH","base_currency_code":"UAH","global_currency_code":"UAH","billing_name":"Александр Сергеевич Гаврилин","billing_address":"4,Кривой Рог,Днепровская,4","shipping_address":"4,Кривой Рог,Днепровская,4","shipping_information":"Доставка на отделение Новой Почты - Новая почта","subtotal":2129,"shipping_and_handling":0,"grand_total":2129,"created_at":"2019-08-17 16:28:40","updated_at":"2019-08-17 16:28:40","base_grand_total":2129},{"entity_id":49,"increment_id":"000000049","state":2,"store_id":1,"store_name":"Main Website\nKlondike\nDefault St","order_id":377,"order_increment_id":"000000377","order_created_at":"2019-08-17 16:32:07","customer_name":"Сергей Александрович Гаврилин","customer_email":"zzzzgavrilin@gmail.com","customer_group_id":1,"payment_method":"cashondelivery","store_currency_code":"UAH","order_currency_code":"UAH","base_currency_code":"UAH","global_currency_code":"UAH","billing_name":"Сергей Александрович Гаврилин","billing_address":"4,Кривой Рог,Днепровская,4","shipping_address":"4,Кривой Рог,Днепровская,4","shipping_information":"Доставка на отделение Новой Почты - Новая почта","subtotal":2129,"shipping_and_handling":0,"grand_total":2129,"created_at":"2019-08-17 16:35:37","updated_at":"2019-08-17 16:35:37","base_grand_total":2129},{"entity_id":50,"increment_id":"000000050","state":2,"store_id":1,"store_name":"Main Website\nKlondike\nDefault St","order_id":371,"order_increment_id":"000000371","order_created_at":"2019-08-17 10:48:07","customer_name":"Антон Головань","customer_email":"obtol1@meta.ua","customer_group_id":1,"payment_method":"cashondelivery","store_currency_code":"UAH","order_currency_code":"UAH","base_currency_code":"UAH","global_currency_code":"UAH","billing_name":"Александр Козак","billing_address":"Новая почта №5,Новоград-Волынский,Житомирская,-","shipping_address":"Новая почта №5,Новоград-Волынский,Житомирская,-","shipping_information":"Доставка на отделение Новой Почты - Новая почта","subtotal":2843,"shipping_and_handling":0,"grand_total":2843,"created_at":"2019-08-17 16:38:55","updated_at":"2019-08-17 16:38:55","base_grand_total":2843},{"entity_id":51,"increment_id":"000000051","state":2,"store_id":1,"store_name":"Main Website\nKlondike\nDefault St","order_id":379,"order_increment_id":"000000379","order_created_at":"2019-08-17 19:18:29","customer_name":"Yurii Malikov","customer_email":"malikov.yurii.a@gmail.com","customer_group_id":1,"payment_method":"cashondelivery","store_currency_code":"UAH","order_currency_code":"UAH","base_currency_code":"UAH","global_currency_code":"UAH","billing_name":"Юрий Маликов","billing_address":"245,Киев,Киевская,-","shipping_address":"245,Киев,Киевская,-","shipping_information":"Доставка на отделение Новой Почты - Новая почта","subtotal":829,"shipping_and_handling":0,"grand_total":746,"created_at":"2019-08-17 19:25:08","updated_at":"2019-08-17 19:25:08","base_grand_total":746},{"entity_id":52,"increment_id":"000000052","state":2,"store_id":1,"store_name":"Main Website\nKlondike\nDefault St","order_id":380,"order_increment_id":"000000380","order_created_at":"2019-08-17 19:30:30","customer_name":"Yurii Malikov","customer_email":"malikov.yurii.a@gmail.com","customer_group_id":1,"payment_method":"checkmo","store_currency_code":"UAH","order_currency_code":"UAH","base_currency_code":"UAH","global_currency_code":"UAH","billing_name":"Юрий Маликов","billing_address":"245,Киев,Киевская,-","shipping_address":"245,Киев,Киевская,-","shipping_information":"Доставка на отделение Новой Почты - Новая почта","subtotal":829,"shipping_and_handling":0,"grand_total":746,"created_at":"2019-08-17 19:33:03","updated_at":"2019-08-17 19:33:03","base_grand_total":746},{"entity_id":53,"increment_id":"000000053","state":2,"store_id":1,"store_name":"Main Website\nKlondike\nDefault St","order_id":381,"order_increment_id":"000000381","order_created_at":"2019-08-18 18:59:04","customer_name":"","customer_email":"kolaboracionist1964@gmail.com","customer_group_id":0,"payment_method":"checkmo","store_currency_code":"UAH","order_currency_code":"UAH","base_currency_code":"UAH","global_currency_code":"UAH","billing_name":"Мария Костова","billing_address":"Отделение 2,Берегово,Закарпатская,-","shipping_address":"Отделение 2,Берегово,Закарпатская,-","shipping_information":"Доставка на отделение Новой Почты - Новая почта","subtotal":2758,"shipping_and_handling":0,"grand_total":2758,"created_at":"2019-08-18 20:36:23","updated_at":"2019-08-18 20:36:23","base_grand_total":2758},{"entity_id":54,"increment_id":"000000054","state":2,"store_id":1,"store_name":"Main Website\nKlondike\nDefault St","order_id":382,"order_increment_id":"000000382","order_created_at":"2019-08-18 20:31:29","customer_name":"","customer_email":"kazlviv@ukr.net","customer_group_id":0,"payment_method":"checkmo","store_currency_code":"UAH","order_currency_code":"UAH","base_currency_code":"UAH","global_currency_code":"UAH","billing_name":"Александр  Казаков","billing_address":"5,Ужгород ,Закарпатская,-","shipping_address":"5,Ужгород ,Закарпатская,-","shipping_information":"Доставка на отделение Новой Почты - Новая почта","subtotal":807,"shipping_and_handling":0,"grand_total":807,"created_at":"2019-08-18 20:43:45","updated_at":"2019-08-18 20:43:45","base_grand_total":807},{"entity_id":55,"increment_id":"000000055","state":2,"store_id":1,"store_name":"Main Website\nKlondike\nDefault St","order_id":383,"order_increment_id":"000000383","order_created_at":"2019-08-18 20:52:32","customer_name":"Юрий Байдык","customer_email":"zzzzbaydik@gmail.com","customer_group_id":1,"payment_method":"checkmo","store_currency_code":"UAH","order_currency_code":"UAH","base_currency_code":"UAH","global_currency_code":"UAH","billing_name":"Юрий Байдык","billing_address":"33,Харьков,Харьковская,33","shipping_address":"33,Харьков,Харьковская,33","shipping_information":"Доставка на отделение Новой Почты - Новая почта","subtotal":7472,"shipping_and_handling":0,"grand_total":7472,"created_at":"2019-08-18 20:52:55","updated_at":"2019-08-18 20:52:55","base_grand_total":7472},{"entity_id":56,"increment_id":"000000056","state":2,"store_id":1,"store_name":"Main Website\nKlondike\nDefault St","order_id":385,"order_increment_id":"000000385","order_created_at":"2019-08-19 08:31:54","customer_name":"Евгений Демин","customer_email":"zzzzdemin@gmail.com","customer_group_id":1,"payment_method":"cashondelivery","store_currency_code":"UAH","order_currency_code":"UAH","base_currency_code":"UAH","global_currency_code":"UAH","billing_name":"Евгений Демин","billing_address":"6,Николаев,Николаевская,6","shipping_address":"6,Николаев,Николаевская,6","shipping_information":"Доставка на отделение Новой Почты - Новая почта","subtotal":829,"shipping_and_handling":0,"grand_total":829,"created_at":"2019-08-19 08:32:16","updated_at":"2019-08-19 08:32:16","base_grand_total":829},{"entity_id":57,"increment_id":"000000057","state":2,"store_id":1,"store_name":"Main Website\nKlondike\nDefault St","order_id":387,"order_increment_id":"000000387","order_created_at":"2019-08-19 12:27:26","customer_name":"Виктория Кузьменко","customer_email":"prsok2@ukr.net","customer_group_id":1,"payment_method":"checkmo","store_currency_code":"UAH","order_currency_code":"UAH","base_currency_code":"UAH","global_currency_code":"UAH","billing_name":"Виктория Кузьменко","billing_address":"235,Киев,Киевская,235","shipping_address":"235,Киев,Киевская,235","shipping_information":"Доставка на отделение Новой Почты - Новая почта","subtotal":938,"shipping_and_handling":0,"grand_total":938,"created_at":"2019-08-19 12:28:03","updated_at":"2019-08-19 12:28:03","base_grand_total":938},{"entity_id":58,"increment_id":"000000058","state":2,"store_id":1,"store_name":"Main Website\nKlondike\nDefault St","order_id":388,"order_increment_id":"000000388","order_created_at":"2019-08-19 12:35:04","customer_name":"Виктор Иванович Югас","customer_email":"zzzzyugas@gmail.com","customer_group_id":1,"payment_method":"cashondelivery","store_currency_code":"UAH","order_currency_code":"UAH","base_currency_code":"UAH","global_currency_code":"UAH","billing_name":"Виктор Иванович Югас","billing_address":"2,Хуст,Закарпатская,2","shipping_address":"2,Хуст,Закарпатская,2","shipping_information":"Доставка на отделение Новой Почты - Новая почта","subtotal":348,"shipping_and_handling":0,"grand_total":348,"created_at":"2019-08-19 12:35:25","updated_at":"2019-08-19 12:35:25","base_grand_total":348},{"entity_id":59,"increment_id":"000000059","state":2,"store_id":1,"store_name":"Main Website\nKlondike\nDefault St","order_id":389,"order_increment_id":"000000389","order_created_at":"2019-08-19 12:42:17","customer_name":"Александр Николаевич Арбузов","customer_email":"aan.matteo@gmail.com","customer_group_id":1,"payment_method":"checkmo","store_currency_code":"UAH","order_currency_code":"UAH","base_currency_code":"UAH","global_currency_code":"UAH","billing_name":"Александр Николаевич Арбузов","billing_address":"37,Киев,Киевская,37","shipping_address":"37,Киев,Киевская,37","shipping_information":"Доставка на отделение Новой Почты - Новая почта","subtotal":255,"shipping_and_handling":0,"grand_total":255,"created_at":"2019-08-19 12:44:44","updated_at":"2019-08-19 12:44:44","base_grand_total":255},{"entity_id":60,"increment_id":"000000060","state":2,"store_id":1,"store_name":"Main Website\nKlondike\nDefault St","order_id":390,"order_increment_id":"000000390","order_created_at":"2019-08-19 12:50:23","customer_name":"Александр Владимирович Терех","customer_email":"zzzztereh@gmail.com","customer_group_id":1,"payment_method":"checkmo","store_currency_code":"UAH","order_currency_code":"UAH","base_currency_code":"UAH","global_currency_code":"UAH","billing_name":"Александр Владимирович Терех","billing_address":"330,Киев,Киевская,330","shipping_address":"330,Киев,Киевская,330","shipping_information":"Доставка на отделение Новой Почты - Новая почта","subtotal":590,"shipping_and_handling":0,"grand_total":590,"created_at":"2019-08-19 12:51:06","updated_at":"2019-08-19 12:51:06","base_grand_total":590},{"entity_id":61,"increment_id":"000000061","state":2,"store_id":1,"store_name":"Main Website\nKlondike\nDefault St","order_id":391,"order_increment_id":"000000391","order_created_at":"2019-08-19 13:17:13","customer_name":"Виталий Александрович Тимченко","customer_email":"zzzztimchenko@gmail.com","customer_group_id":1,"payment_method":"cashondelivery","store_currency_code":"UAH","order_currency_code":"UAH","base_currency_code":"UAH","global_currency_code":"UAH","billing_name":"Виталий Александрович Тимченко","billing_address":"74,Одесса,Одесская,74","shipping_address":"74,Одесса,Одесская,74","shipping_information":"Доставка на отделение Новой Почты - Новая почта","subtotal":2943,"shipping_and_handling":0,"grand_total":2943,"created_at":"2019-08-19 13:17:35","updated_at":"2019-08-19 13:17:35","base_grand_total":2943},{"entity_id":62,"increment_id":"000000062","state":2,"store_id":1,"store_name":"Main Website\nKlondike\nDefault St","order_id":392,"order_increment_id":"000000392","order_created_at":"2019-08-19 13:22:53","customer_name":"Анна Коновалова","customer_email":"zzzzkonovalova@gmail.com","customer_group_id":1,"payment_method":"cashondelivery","store_currency_code":"UAH","order_currency_code":"UAH","base_currency_code":"UAH","global_currency_code":"UAH","billing_name":"Анна Коновалова","billing_address":"122,Одесса,Одесская,122","shipping_address":"122,Одесса,Одесская,122","shipping_information":"Доставка на отделение Новой Почты - Новая почта","subtotal":515,"shipping_and_handling":0,"grand_total":515,"created_at":"2019-08-19 13:23:25","updated_at":"2019-08-19 13:23:25","base_grand_total":515},{"entity_id":63,"increment_id":"000000063","state":2,"store_id":1,"store_name":"Main Website\nKlondike\nDefault St","order_id":393,"order_increment_id":"000000393","order_created_at":"2019-08-19 14:03:44","customer_name":"Марина Фесенко","customer_email":"zzzzfesenko@gmail.com","customer_group_id":1,"payment_method":"cashondelivery","store_currency_code":"UAH","order_currency_code":"UAH","base_currency_code":"UAH","global_currency_code":"UAH","billing_name":"Марина Фесенко","billing_address":"9,Полтава,Полтавская,9","shipping_address":"9,Полтава,Полтавская,9","shipping_information":"Доставка на отделение Новой Почты - Новая почта","subtotal":95,"shipping_and_handling":0,"grand_total":95,"created_at":"2019-08-19 14:04:05","updated_at":"2019-08-19 14:04:05","base_grand_total":95},{"entity_id":64,"increment_id":"000000064","state":2,"store_id":1,"store_name":"Main Website\nKlondike\nDefault St","order_id":396,"order_increment_id":"000000396","order_created_at":"2019-08-20 11:49:12","customer_name":"Татьяна Пащетник","customer_email":"zzzzpashetnik@gmail.com","customer_group_id":1,"payment_method":"checkmo","store_currency_code":"UAH","order_currency_code":"UAH","base_currency_code":"UAH","global_currency_code":"UAH","billing_name":"Татьяна Пащетник","billing_address":"1,Борислав,Львовская,1","shipping_address":"1,Борислав,Львовская,1","shipping_information":"Доставка на отделение Новой Почты - Новая почта","subtotal":955,"shipping_and_handling":0,"grand_total":955,"created_at":"2019-08-20 11:49:43","updated_at":"2019-08-20 11:49:43","base_grand_total":955},{"entity_id":65,"increment_id":"000000065","state":2,"store_id":1,"store_name":"Main Website\nKlondike\nDefault St","order_id":397,"order_increment_id":"000000397","order_created_at":"2019-08-20 12:17:05","customer_name":"Александр Клименко","customer_email":"ecopozota1981@gmail.com","customer_group_id":1,"payment_method":"cashondelivery","store_currency_code":"UAH","order_currency_code":"UAH","base_currency_code":"UAH","global_currency_code":"UAH","billing_name":"Александр Клименко","billing_address":"3,Винница,Винницкая,3","shipping_address":"3,Винница,Винницкая,3","shipping_information":"Доставка на отделение Новой Почты - Новая почта","subtotal":2090,"shipping_and_handling":0,"grand_total":2090,"created_at":"2019-08-20 12:17:19","updated_at":"2019-08-20 12:17:19","base_grand_total":2090},{"entity_id":66,"increment_id":"000000066","state":2,"store_id":1,"store_name":"Main Website\nKlondike\nDefault St","order_id":394,"order_increment_id":"000000394","order_created_at":"2019-08-20 10:16:20","customer_name":"","customer_email":"elenlopez888@gmail.com","customer_group_id":0,"payment_method":"cashondelivery","store_currency_code":"UAH","order_currency_code":"UAH","base_currency_code":"UAH","global_currency_code":"UAH","billing_name":"Елена Иванова","billing_address":"66 отделение новой почты,Днепр,Днепровская,-","shipping_address":"66 отделение новой почты,Днепр,Днепровская,-","shipping_information":"Доставка на отделение Новой Почты - Новая почта","subtotal":95,"shipping_and_handling":0,"grand_total":95,"created_at":"2019-08-20 12:18:07","updated_at":"2019-08-20 12:18:07","base_grand_total":95},{"entity_id":67,"increment_id":"000000067","state":2,"store_id":1,"store_name":"Main Website\nKlondike\nDefault St","order_id":395,"order_increment_id":"000000395","order_created_at":"2019-08-20 11:39:06","customer_name":"Вероника Богачёва","customer_email":"bogacheva.11@meta.ua","customer_group_id":1,"payment_method":"cashondelivery","store_currency_code":"UAH","order_currency_code":"UAH","base_currency_code":"UAH","global_currency_code":"UAH","billing_name":"Вероника Богачёва","billing_address":"Отделение №4,Коростень,Житомирская ,-","shipping_address":"Отделение №4,Коростень,Житомирская ,-","shipping_information":"Доставка на отделение Новой Почты - Новая почта","subtotal":230,"shipping_and_handling":0,"grand_total":230,"created_at":"2019-08-20 12:19:03","updated_at":"2019-08-20 12:19:03","base_grand_total":230},{"entity_id":68,"increment_id":"000000068","state":2,"store_id":1,"store_name":"Main Website\nKlondike\nDefault St","order_id":398,"order_increment_id":"000000398","order_created_at":"2019-08-20 12:24:22","customer_name":"Иван Павлович Дубиняк","customer_email":"zzzzdubinyak@gmail.com","customer_group_id":1,"payment_method":"cashondelivery","store_currency_code":"UAH","order_currency_code":"UAH","base_currency_code":"UAH","global_currency_code":"UAH","billing_name":"Иван Павлович Дубиняк","billing_address":"1,Брюховичи,Львовская,1","shipping_address":"1,Брюховичи,Львовская,1","shipping_information":"Доставка на отделение Новой Почты - Новая почта","subtotal":478,"shipping_and_handling":0,"grand_total":478,"created_at":"2019-08-20 12:27:53","updated_at":"2019-08-20 12:27:53","base_grand_total":478},{"entity_id":69,"increment_id":"000000069","state":2,"store_id":1,"store_name":"Main Website\nKlondike\nDefault St","order_id":399,"order_increment_id":"000000399","order_created_at":"2019-08-20 14:15:24","customer_name":"Александр Клименко","customer_email":"ecopozota1981@gmail.com","customer_group_id":1,"payment_method":"cashondelivery","store_currency_code":"UAH","order_currency_code":"UAH","base_currency_code":"UAH","global_currency_code":"UAH","billing_name":"Александр Клименко","billing_address":"3,Винница,Винницкая,3","shipping_address":"3,Винница,Винницкая,3","shipping_information":"Доставка на отделение Новой Почты - Новая почта","subtotal":2553,"shipping_and_handling":0,"grand_total":2553,"created_at":"2019-08-20 16:43:52","updated_at":"2019-08-20 16:43:52","base_grand_total":2553},{"entity_id":70,"increment_id":"000000070","state":2,"store_id":1,"store_name":"Main Website\nKlondike\nDefault St","order_id":400,"order_increment_id":"000000400","order_created_at":"2019-08-20 16:49:18","customer_name":"Александр Мороз","customer_email":"zzzzmoroz@gmail.com","customer_group_id":1,"payment_method":"checkmo","store_currency_code":"UAH","order_currency_code":"UAH","base_currency_code":"UAH","global_currency_code":"UAH","billing_name":"Александр Мороз","billing_address":"6,Чернигов,Черниговская,6","shipping_address":"6,Чернигов,Черниговская,6","shipping_information":"Доставка на отделение Новой Почты - Новая почта","subtotal":659,"shipping_and_handling":0,"grand_total":659,"created_at":"2019-08-20 16:51:04","updated_at":"2019-08-20 16:51:04","base_grand_total":659},{"entity_id":71,"increment_id":"000000071","state":2,"store_id":1,"store_name":"Main Website\nKlondike\nDefault St","order_id":401,"order_increment_id":"000000401","order_created_at":"2019-08-20 18:27:00","customer_name":"","customer_email":"manoylo.m.r@gmail.com","customer_group_id":0,"payment_method":"wayforpay","store_currency_code":"UAH","order_currency_code":"UAH","base_currency_code":"UAH","global_currency_code":"UAH","billing_name":"Мария Манойло","billing_address":"НП №62,Киев,Киевская,-","shipping_address":"НП №62,Киев,Киевская,-","shipping_information":"Доставка на отделение Новой Почты - Новая почта","subtotal":1296,"shipping_and_handling":0,"grand_total":1296,"created_at":"2019-08-20 18:54:58","updated_at":"2019-08-20 18:54:58","base_grand_total":1296},{"entity_id":72,"increment_id":"000000072","state":2,"store_id":1,"store_name":"Main Website\nKlondike\nDefault St","order_id":402,"order_increment_id":"000000402","order_created_at":"2019-08-21 10:41:57","customer_name":"","customer_email":"olesiacord73@gmail.com","customer_group_id":0,"payment_method":"cashondelivery","store_currency_code":"UAH","order_currency_code":"UAH","base_currency_code":"UAH","global_currency_code":"UAH","billing_name":"Олеся Федоренко","billing_address":"навая пошта 2,Жмеринка,Винницкая,-","shipping_address":"навая пошта 2,Жмеринка,Винницкая,-","shipping_information":"Доставка на отделение Новой Почты - Новая почта","subtotal":348,"shipping_and_handling":0,"grand_total":348,"created_at":"2019-08-21 11:22:48","updated_at":"2019-08-21 11:22:48","base_grand_total":348},{"entity_id":73,"increment_id":"000000073","state":2,"store_id":1,"store_name":"Main Website\nKlondike\nDefault St","order_id":404,"order_increment_id":"000000404","order_created_at":"2019-08-21 11:10:54","customer_name":"","customer_email":"efrantisova@gmail.com","customer_group_id":0,"payment_method":"cashondelivery","store_currency_code":"UAH","order_currency_code":"UAH","base_currency_code":"UAH","global_currency_code":"UAH","billing_name":"Евгения  Франтисова","billing_address":"Отделение 1,С. Новые Петровцы ,Киевская,-","shipping_address":"Отделение 1,С. Новые Петровцы ,Киевская,-","shipping_information":"Доставка на отделение Новой Почты - Новая почта","subtotal":220,"shipping_and_handling":0,"grand_total":220,"created_at":"2019-08-21 11:24:29","updated_at":"2019-08-21 11:24:29","base_grand_total":220},{"entity_id":74,"increment_id":"000000074","state":2,"store_id":1,"store_name":"Main Website\nKlondike\nDefault St","order_id":403,"order_increment_id":"000000403","order_created_at":"2019-08-21 10:44:27","customer_name":"","customer_email":"levonti.m@rambler.ru","customer_group_id":0,"payment_method":"checkmo","store_currency_code":"UAH","order_currency_code":"UAH","base_currency_code":"UAH","global_currency_code":"UAH","billing_name":"Екатерина Вериенко","billing_address":"отд. 1.,Княжичи,Киевская,-","shipping_address":"отд. 1.,Княжичи,Киевская,-","shipping_information":"Доставка на отделение Новой Почты - Новая почта","subtotal":545,"shipping_and_handling":0,"grand_total":545,"created_at":"2019-08-21 11:25:37","updated_at":"2019-08-21 11:25:37","base_grand_total":545},{"entity_id":75,"increment_id":"000000075","state":2,"store_id":1,"store_name":"Main Website\nKlondike\nDefault St","order_id":405,"order_increment_id":"000000405","order_created_at":"2019-08-21 12:03:42","customer_name":"Анжела Владимировна Глазунова","customer_email":"zzzzglazunova@gmail.com","customer_group_id":1,"payment_method":"checkmo","store_currency_code":"UAH","order_currency_code":"UAH","base_currency_code":"UAH","global_currency_code":"UAH","billing_name":"Анжела Владимировна Глазунова","billing_address":"237,Киев,Киевская,237","shipping_address":"237,Киев,Киевская,237","shipping_information":"Доставка на отделение Новой Почты - Новая почта","subtotal":147,"shipping_and_handling":0,"grand_total":147,"created_at":"2019-08-21 12:04:06","updated_at":"2019-08-21 12:04:06","base_grand_total":147},{"entity_id":76,"increment_id":"000000076","state":2,"store_id":1,"store_name":"Main Website\nKlondike\nDefault St","order_id":408,"order_increment_id":"000000408","order_created_at":"2019-08-21 15:47:22","customer_name":"Виталий Александрович Лесько","customer_email":"zzzzlesko@gmail.com","customer_group_id":1,"payment_method":"checkmo","store_currency_code":"UAH","order_currency_code":"UAH","base_currency_code":"UAH","global_currency_code":"UAH","billing_name":"Виталий Александрович Лесько","billing_address":"1,Ирпень,Киевская,1","shipping_address":"1,Ирпень,Киевская,1","shipping_information":"Доставка на отделение Новой Почты - Новая почта","subtotal":545,"shipping_and_handling":0,"grand_total":545,"created_at":"2019-08-21 15:47:42","updated_at":"2019-08-21 15:47:42","base_grand_total":545},{"entity_id":77,"increment_id":"000000077","state":2,"store_id":1,"store_name":"Main Website\nKlondike\nDefault St","order_id":413,"order_increment_id":"000000413","order_created_at":"2019-08-21 19:06:58","customer_name":"Вадим Рыбак","customer_email":"kit.mehanik.360@gmail.com","customer_group_id":1,"payment_method":"wayforpay","store_currency_code":"UAH","order_currency_code":"UAH","base_currency_code":"UAH","global_currency_code":"UAH","billing_name":"Вадим Рыбак","billing_address":"нп10,Хмельницкий,Хмельницкая,-","shipping_address":"нп10,Хмельницкий,Хмельницкая,-","shipping_information":"Доставка на отделение Новой Почты - Новая почта","subtotal":914,"shipping_and_handling":0,"grand_total":914,"created_at":"2019-08-21 19:07:22","updated_at":"2019-08-21 19:07:22","base_grand_total":914},{"entity_id":78,"increment_id":"000000078","state":2,"store_id":1,"store_name":"Main Website\nKlondike\nDefault St","order_id":418,"order_increment_id":"000000418","order_created_at":"2019-08-22 07:29:58","customer_name":"Сергей Бусыгин","customer_email":"sb611961@ukr.net","customer_group_id":1,"payment_method":"cashondelivery","store_currency_code":"UAH","order_currency_code":"UAH","base_currency_code":"UAH","global_currency_code":"UAH","billing_name":"Сергей Бусыгин","billing_address":"26,Днепр,днепропетровская,-","shipping_address":"26,Днепр,днепропетровская,-","shipping_information":"Доставка на отделение Новой Почты - Новая почта","subtotal":315,"shipping_and_handling":0,"grand_total":315,"created_at":"2019-08-22 08:19:00","updated_at":"2019-08-22 08:19:00","base_grand_total":315},{"entity_id":79,"increment_id":"000000079","state":2,"store_id":1,"store_name":"Main Website\nKlondike\nDefault St","order_id":419,"order_increment_id":"000000419","order_created_at":"2019-08-22 09:20:56","customer_name":"Руслан Захарович Моцпан","customer_email":"zzzzmozpan@gmail.com","customer_group_id":1,"payment_method":"cashondelivery","store_currency_code":"UAH","order_currency_code":"UAH","base_currency_code":"UAH","global_currency_code":"UAH","billing_name":"Руслан Захарович Моцпан","billing_address":"15,Винница,Винницкая,15","shipping_address":"15,Винница,Винницкая,15","shipping_information":"Доставка на отделение Новой Почты - Новая почта","subtotal":295,"shipping_and_handling":0,"grand_total":295,"created_at":"2019-08-22 09:21:12","updated_at":"2019-08-22 09:21:12","base_grand_total":295},{"entity_id":80,"increment_id":"000000080","state":2,"store_id":1,"store_name":"Main Website\nKlondike\nDefault St","order_id":421,"order_increment_id":"000000421","order_created_at":"2019-08-22 16:20:15","customer_name":"Александр Клименко","customer_email":"ecopozota1981@gmail.com","customer_group_id":1,"payment_method":"checkmo","store_currency_code":"UAH","order_currency_code":"UAH","base_currency_code":"UAH","global_currency_code":"UAH","billing_name":"Александр Клименко","billing_address":"3,Винница,Винницкая,3","shipping_address":"3,Винница,Винницкая,3","shipping_information":"Доставка на отделение Новой Почты - Новая почта","subtotal":1518,"shipping_and_handling":0,"grand_total":1518,"created_at":"2019-08-22 16:20:38","updated_at":"2019-08-22 16:20:38","base_grand_total":1518},{"entity_id":81,"increment_id":"000000081","state":2,"store_id":1,"store_name":"Main Website\nKlondike\nDefault St","order_id":423,"order_increment_id":"000000423","order_created_at":"2019-08-22 16:33:31","customer_name":"Юрий Байдык","customer_email":"baidyk77@gmail.com","customer_group_id":1,"payment_method":"checkmo","store_currency_code":"UAH","order_currency_code":"UAH","base_currency_code":"UAH","global_currency_code":"UAH","billing_name":"Юрий Байдык","billing_address":"33,Харьков,Харьковская,33","shipping_address":"33,Харьков,Харьковская,33","shipping_information":"Доставка на отделение Новой Почты - Новая почта","subtotal":14840,"shipping_and_handling":0,"grand_total":14840,"created_at":"2019-08-22 16:33:48","updated_at":"2019-08-22 16:33:48","base_grand_total":14840},{"entity_id":82,"increment_id":"000000082","state":2,"store_id":1,"store_name":"Main Website\nKlondike\nDefault St","order_id":422,"order_increment_id":"000000422","order_created_at":"2019-08-22 16:30:07","customer_name":"","customer_email":"difleur.mail@gmail.com","customer_group_id":0,"payment_method":"wayforpay","store_currency_code":"UAH","order_currency_code":"UAH","base_currency_code":"UAH","global_currency_code":"UAH","billing_name":"Наталия Криминская","billing_address":"2,Бородянка,Киевская,-","shipping_address":"2,Бородянка,Киевская,-","shipping_information":"Доставка на отделение Новой Почты - Новая почта","subtotal":305,"shipping_and_handling":0,"grand_total":305,"created_at":"2019-08-22 16:40:49","updated_at":"2019-08-22 16:40:49","base_grand_total":305},{"entity_id":83,"increment_id":"000000083","state":2,"store_id":1,"store_name":"Main Website\nKlondike\nDefault St","order_id":424,"order_increment_id":"000000424","order_created_at":"2019-08-22 16:58:32","customer_name":"","customer_email":"difleur.mail@gmail.com","customer_group_id":0,"payment_method":"checkmo","store_currency_code":"UAH","order_currency_code":"UAH","base_currency_code":"UAH","global_currency_code":"UAH","billing_name":"Наталия Криминская","billing_address":"2,Бородянка,Киевская,2","shipping_address":"2,Бородянка,Киевская,2","shipping_information":"Доставка на отделение Новой Почты - Новая почта","subtotal":305,"shipping_and_handling":0,"grand_total":305,"created_at":"2019-08-22 16:59:55","updated_at":"2019-08-22 16:59:55","base_grand_total":305},{"entity_id":84,"increment_id":"000000084","state":2,"store_id":1,"store_name":"Main Website\nKlondike\nDefault St","order_id":425,"order_increment_id":"000000425","order_created_at":"2019-08-22 17:07:16","customer_name":"","customer_email":"anna.avtor.rabot@gmail.com","customer_group_id":0,"payment_method":"checkmo","store_currency_code":"UAH","order_currency_code":"UAH","base_currency_code":"UAH","global_currency_code":"UAH","billing_name":"Анна Лободюк","billing_address":"14,Сумы,Сумская,-","shipping_address":"14,Сумы,Сумская,-","shipping_information":"Доставка на отделение Новой Почты - Новая почта","subtotal":32,"shipping_and_handling":0,"grand_total":32,"created_at":"2019-08-22 17:07:58","updated_at":"2019-08-22 17:07:58","base_grand_total":32},{"entity_id":86,"increment_id":"000000086","state":2,"store_id":1,"store_name":"Main Website\nKlondike\nDefault St","order_id":428,"order_increment_id":"000000428","order_created_at":"2019-08-22 17:19:16","customer_name":"Владимир Перехрест","customer_email":"zzzzperehrest@gmail.com","customer_group_id":1,"payment_method":"cashondelivery","store_currency_code":"UAH","order_currency_code":"UAH","base_currency_code":"UAH","global_currency_code":"UAH","billing_name":"Владимир Перехрест","billing_address":"6,Бровари,Киевская,6","shipping_address":"6,Бровари,Киевская,6","shipping_information":"Доставка на отделение Новой Почты - Новая почта","subtotal":310,"shipping_and_handling":0,"grand_total":310,"created_at":"2019-08-22 17:20:29","updated_at":"2019-08-22 17:20:29","base_grand_total":310},{"entity_id":87,"increment_id":"000000087","state":2,"store_id":1,"store_name":"Main Website\nKlondike\nDefault St","order_id":426,"order_increment_id":"000000426","order_created_at":"2019-08-22 17:10:02","customer_name":"Александр Клименко","customer_email":"ecopozota1981@gmail.com","customer_group_id":1,"payment_method":"cashondelivery","store_currency_code":"UAH","order_currency_code":"UAH","base_currency_code":"UAH","global_currency_code":"UAH","billing_name":"Александр Клименко","billing_address":"3,Винница,Винницкая,3","shipping_address":"3,Винница,Винницкая,3","shipping_information":"Доставка на отделение Новой Почты - Новая почта","subtotal":640,"shipping_and_handling":0,"grand_total":640,"created_at":"2019-08-22 17:23:47","updated_at":"2019-08-22 17:23:47","base_grand_total":640},{"entity_id":88,"increment_id":"000000088","state":2,"store_id":1,"store_name":"Main Website\nKlondike\nDefault St","order_id":429,"order_increment_id":"000000429","order_created_at":"2019-08-23 08:06:47","customer_name":"","customer_email":"freemail.nadya@ukr.net","customer_group_id":0,"payment_method":"checkmo","store_currency_code":"UAH","order_currency_code":"UAH","base_currency_code":"UAH","global_currency_code":"UAH","billing_name":"Елена Холод","billing_address":"1,Копайгород,Винницкая,-","shipping_address":"1,Копайгород,Винницкая,-","shipping_information":"Доставка на отделение Новой Почты - Новая почта","subtotal":1054,"shipping_and_handling":0,"grand_total":1054,"created_at":"2019-08-23 08:41:30","updated_at":"2019-08-23 08:41:30","base_grand_total":1054},{"entity_id":89,"increment_id":"000000089","state":2,"store_id":1,"store_name":"Main Website\nKlondike\nDefault St","order_id":430,"order_increment_id":"000000430","order_created_at":"2019-08-23 11:09:19","customer_name":"Евгений Юрьевич Петров","customer_email":"zzzzpetrov@gmail.com","customer_group_id":1,"payment_method":"cashondelivery","store_currency_code":"UAH","order_currency_code":"UAH","base_currency_code":"UAH","global_currency_code":"UAH","billing_name":"Евгений Юрьевич Петров","billing_address":"17,Днепр,Днепровская,17","shipping_address":"17,Днепр,Днепровская,17","shipping_information":"Доставка на отделение Новой Почты - Новая почта","subtotal":1051,"shipping_and_handling":0,"grand_total":1051,"created_at":"2019-08-23 11:09:38","updated_at":"2019-08-23 11:09:38","base_grand_total":1051},{"entity_id":90,"increment_id":"000000090","state":2,"store_id":1,"store_name":"Main Website\nKlondike\nDefault St","order_id":433,"order_increment_id":"000000433","order_created_at":"2019-08-24 06:50:51","customer_name":"Светлана Санду","customer_email":"zzzzsanduk@gmail.com","customer_group_id":1,"payment_method":"cashondelivery","store_currency_code":"UAH","order_currency_code":"UAH","base_currency_code":"UAH","global_currency_code":"UAH","billing_name":"Светлана Санду","billing_address":"50,Киев,Киевская,50","shipping_address":"50,Киев,Киевская,50","shipping_information":"Доставка на отделение Новой Почты - Новая почта","subtotal":1410,"shipping_and_handling":0,"grand_total":1410,"created_at":"2019-08-24 06:51:12","updated_at":"2019-08-24 06:51:12","base_grand_total":1410},{"entity_id":91,"increment_id":"000000091","state":2,"store_id":1,"store_name":"Main Website\nKlondike\nDefault St","order_id":432,"order_increment_id":"000000432","order_created_at":"2019-08-23 13:48:57","customer_name":"Роман Леонидович Воронин","customer_email":"zzzzvoronin@gmail.com","customer_group_id":1,"payment_method":"checkmo","store_currency_code":"UAH","order_currency_code":"UAH","base_currency_code":"UAH","global_currency_code":"UAH","billing_name":"Роман Леонидович Воронин","billing_address":"104,Одесса,Одесская,104","shipping_address":"104,Одесса,Одесская,104","shipping_information":"Доставка на отделение Новой Почты - Новая почта","subtotal":161,"shipping_and_handling":0,"grand_total":161,"created_at":"2019-08-24 06:54:20","updated_at":"2019-08-24 06:54:20","base_grand_total":161},{"entity_id":92,"increment_id":"000000092","state":2,"store_id":1,"store_name":"Main Website\nKlondike\nDefault St","order_id":431,"order_increment_id":"000000431","order_created_at":"2019-08-23 13:47:29","customer_name":"","customer_email":"0675667746a@ukr.net","customer_group_id":0,"payment_method":"cashondelivery","store_currency_code":"UAH","order_currency_code":"UAH","base_currency_code":"UAH","global_currency_code":"UAH","billing_name":"Василий Поляков","billing_address":"9,Днепр,Днипровська,-","shipping_address":"9,Днепр,Днипровська,-","shipping_information":"Доставка на отделение Новой Почты - Новая почта","subtotal":105,"shipping_and_handling":0,"grand_total":105,"created_at":"2019-08-24 13:06:19","updated_at":"2019-08-24 13:06:19","base_grand_total":105},{"entity_id":93,"increment_id":"000000093","state":2,"store_id":1,"store_name":"Main Website\nKlondike\nDefault Store View","order_id":441,"order_increment_id":"000000444","order_created_at":"2020-01-07 12:19:19","customer_name":"test first test last","customer_email":"test@test.test","customer_group_id":1,"payment_method":"cashondelivery","store_currency_code":"UAH","order_currency_code":"UAH","base_currency_code":"UAH","global_currency_code":"UAH","billing_name":"test first test last","billing_address":"test street,test city,test post","shipping_address":"test street,test city,test post","shipping_information":"Доставка на отделение Новой Почты - Новая почта","subtotal":115,"shipping_and_handling":0,"grand_total":115,"created_at":"2020-01-20 20:24:41","updated_at":"2020-01-20 20:24:41","base_grand_total":115}]